{
  "Camera": {
    "Position": [
      -3.0,
      -3.0,
      2.5
    ],
    "Rotation": [
      45.0,
      -30.0
    ]
  },
  "Materials": [
    "Assets/Materials/M_BlueColor.json",
    "Assets/Materials/M_Hologram.json",
    "Assets/Materials/M_Gizmos.json",
    "Assets/Materials/M_GreenColor.json",
    "Assets/Materials/M_SolidWireframeFill.json",
    "Assets/Materials/M_RedColor.json",
    "Assets/Materials/M_Sky.json",
    "Assets/Materials/M_TintYellow.json",
    "Assets/Materials/M_SolidWireframeLine.json",
    "Assets/Materials/M_StaticMesh.json",
    "Assets/Materials/M_Wireframe.json"
  ],
  "NextUUID": 15,
  "PerspectiveCamera": {
    "FOV": 45.0,
    "FarClip": 1000.0,
    "Location": [
      -163.1998291015625,
      8.04511547088623,
      30.966991424560547
    ],
    "NearClip": 0.10000000149011612,
    "Rotation": [
      -0.2000042051076889,
      -7.400059700012207
    ]
  },
  "Primitives": {
    "0": {
      "Billboard": true,
      "Class": "AStaticMeshActor",
      "ComponentUUIDs": [
        5,
        6
      ],
      "Location": [
        -6.008644104003906,
        4.737079620361328,
        17.09674072265625
      ],
      "ObjStaticMeshAsset": "Assets/Meshes/warning_01.dasset",
      "Rotation": [
        -0.0,
        0.0,
        -0.0
      ],
      "Scale": [
        23.475000381469727,
        24.69451141357422,
        23.475000381469727
      ],
      "Text": "Text",
      "TextColor": [
        1.0,
        1.0,
        1.0,
        1.0
      ],
      "Type": "StaticMeshComp",
      "UUID": 4
    },
    "1": {
      "Billboard": true,
      "Class": "AStaticMeshActor",
      "ComponentUUIDs": [
        9,
        10
      ],
      "Location": [
        3.1832237243652344,
        0.04436519369482994,
        0.846580982208252
      ],
      "ObjStaticMeshAsset": "Assets/Meshes/scene.dasset",
      "Rotation": [
        -0.0,
        0.0,
        -123.44145202636719
      ],
      "Scale": [
        1.0,
        1.0,
        1.0
      ],
      "Text": "Text",
      "TextColor": [
        1.0,
        1.0,
        1.0,
        1.0
      ],
      "Type": "StaticMeshComp",
      "UUID": 8
    },
    "2": {
      "Billboard": true,
      "Class": "ASkySphereActor",
      "ComponentUUIDs": [
        13,
        14
      ],
      "Location": [
        -3.0,
        -3.0,
        2.5
      ],
      "ObjStaticMeshAsset": "Engine/BasicShapes/SkySphere",
      "Rotation": [
        -0.0,
        0.0,
        -0.0
      ],
      "Scale": [
        2000.0,
        2000.0,
        2000.0
      ],
      "Text": "Text",
      "TextColor": [
        1.0,
        1.0,
        1.0,
        1.0
      ],
      "Type": "StaticMeshComp",
      "UUID": 12
    }
  }
}
